concretefhe_utils-0.0.10-py3.9-nspkg.pth
concretefhe/utils/__init__.py
concretefhe/utils/file.py
concretefhe_utils-0.0.10.dist-info/LICENSE
concretefhe_utils-0.0.10.dist-info/METADATA
concretefhe_utils-0.0.10.dist-info/WHEEL
concretefhe_utils-0.0.10.dist-info/namespace_packages.txt
concretefhe_utils-0.0.10.dist-info/top_level.txt
concretefhe_utils-0.0.10.dist-info/RECORD
